README.rst
setup.py
sanic_crud/__init__.py
sanic_crud/config.py
sanic_crud/crud_generation.py
sanic_crud.egg-info/PKG-INFO
sanic_crud.egg-info/SOURCES.txt
sanic_crud.egg-info/dependency_links.txt
sanic_crud.egg-info/requires.txt
sanic_crud.egg-info/top_level.txt
sanic_crud/resources/__init__.py
sanic_crud/resources/base_resource.py
sanic_crud/resources/collection_resource.py
sanic_crud/resources/single_resource.py